README.md
setup.py
pyebnf/__init__.py
pyebnf/_hand_written_parser.py
pyebnf/compiler.py
pyebnf/exception.py
pyebnf/operator.py
pyebnf/parser.py
pyebnf/parser_base.py
pyebnf/primitive.py
pyebnf/util.py
pyebnf.egg-info/PKG-INFO
pyebnf.egg-info/SOURCES.txt
pyebnf.egg-info/dependency_links.txt
pyebnf.egg-info/top_level.txt