Metadata-Version: 1.1
Name: pyebnf
Version: 0.1.2
Summary: An EBNF compiler
Home-page: https://github.com/treycucco/pyebnf
Author: Trey Cucco
Author-email: fcucco@gmail.com
License: MIT
Download-URL: https://github.com/treycucco/pyebnf/tarball/master
Platform: any
Classifier: Development Status :: 4 - Beta
Classifier: Intended Audience :: Developers
Classifier: License :: OSI Approved :: MIT License
Classifier: Natural Language :: English
Classifier: Operating System :: OS Independent
Classifier: Programming Language :: Python
Classifier: Programming Language :: Python :: 3 :: Only
Classifier: Programming Language :: Python :: 3.4
